ugpt/__init__.py
ugpt/__main__.py
ugpt/bin.py
ugpt/chat.py
ugpt/completion.py
ugpt/edit.py
ugpt/image.py
ugpt/server.py
ugpt/schemas/__init__.py
ugpt/schemas/base.py
ugpt/schemas/model.py
uGPT-0.1.2.dist-info/LICENSE
uGPT-0.1.2.dist-info/METADATA
uGPT-0.1.2.dist-info/WHEEL
uGPT-0.1.2.dist-info/entry_points.txt
uGPT-0.1.2.dist-info/top_level.txt
uGPT-0.1.2.dist-info/RECORD
