Metadata-Version: 2.1
Name: uGPT
Version: 0.1.2
Summary: An easy to use API and CLI wrapper for chatGPT and other AIGC API base on utype
Home-page: https://github.com/voidZXL/ugpt
Author: 周煦林 (XuLin Zhou)
Author-email: zxl@utilmeta.com
License: https://opensource.org/license/mit/
Project-URL: Project Home, https://github.com/voidZXL/ugpt
Project-URL: Documentation, https://github.com/voidZXL/ugpt
Project-URL: Source Code, https://github.com/voidZXL/ugpt
Keywords: ugpt gpt chatgpt openai utype api
Platform: UNKNOWN
Classifier: Development Status :: 3 - Alpha
Classifier: Programming Language :: Python
Classifier: Programming Language :: Python :: 3
Classifier: Programming Language :: Python :: 3 :: Only
Classifier: Programming Language :: Python :: 3.7
Classifier: Programming Language :: Python :: 3.8
Classifier: Programming Language :: Python :: 3.9
Classifier: Programming Language :: Python :: 3.10
Classifier: Programming Language :: Python :: 3.11
Classifier: Intended Audience :: Developers
Classifier: Intended Audience :: Information Technology
Classifier: Intended Audience :: System Administrators
Classifier: License :: OSI Approved :: MIT License
Classifier: Operating System :: OS Independent
Classifier: Topic :: Software Development :: Libraries :: Python Modules
Classifier: Topic :: Internet
Requires-Python: >=3.7
License-File: LICENSE
Requires-Dist: utype
